requests_file_adapter/__init__.py
requests_file_adapter/adapter.py
requests_file_adapter/ip.py
requests_file_adapter/utils.py
requests_file_adapter/version.py
requests_file_adapter-2024.2.dist-info/METADATA
requests_file_adapter-2024.2.dist-info/WHEEL
requests_file_adapter-2024.2.dist-info/licenses/LICENSE.txt
requests_file_adapter-2024.2.dist-info/RECORD
