Metadata-Version: 2.3
Name: Requests_File_Adapter
Version: 2024.2
Summary: File adapter for the Requests library.
Project-URL: Homepage, https://gitlab.inria.fr/jrye/requests-file-adapter
Project-URL: Source, https://gitlab.inria.fr/jrye/requests-file-adapter.git
Project-URL: Documentation, https://jrye.gitlabpages.inria.fr/requests-file-adapter
Project-URL: Issues, https://gitlab.inria.fr/jrye/requests-file-adapter/-/issues
Author-email: Jan-Michael Rye <jan-michael.rye@inria.fr>
License: MIT License
License-File: LICENSE.txt
Classifier: License :: OSI Approved :: MIT License
Classifier: Operating System :: OS Independent
Classifier: Programming Language :: Python :: 3
Requires-Python: >=3.6
Requires-Dist: psutil
Requires-Dist: requests
